chchart_parser/__init__.py
chchart_parser/__main__.py
chchart_parser/chart.py
chchart_parser/chart_metadata.py
chchart_parser/enums.py
chchart_parser/events.py
chchart_parser/note_chart.py
chchart_parser/sync.py
chchart_parser-1.2.0.dist-info/LICENSE
chchart_parser-1.2.0.dist-info/WHEEL
chchart_parser-1.2.0.dist-info/METADATA
chchart_parser-1.2.0.dist-info/RECORD
