Metadata-Version: 2.1
Name: chchart-parser
Version: 1.2.0
Summary: Parser for clone hero .chart files
License: MIT
Author: Dogeek
Author-email: simon.bordeyne@gmail.com
Requires-Python: >=3.10,<4.0
Classifier: License :: OSI Approved :: MIT License
Classifier: Programming Language :: Python :: 3
Classifier: Programming Language :: Python :: 3.10
Classifier: Programming Language :: Python :: 3.10
Classifier: Programming Language :: Python :: 3.7
Classifier: Programming Language :: Python :: 3.8
Classifier: Programming Language :: Python :: 3.9
